qianxing_openapi/__init__.py
qianxing_openapi/client.py
qianxing_openapi/http_client.py
qianxing_openapi/main.py
qianxing_openapi/process_task.py
qianxing_openapi/process_task_model.py
qianxing_openapi/qxmap_model.py
qianxing_openapi/request_model.py
qianxing_openapi/request_struct.py
qianxing_openapi/resources.py
qianxing_openapi/response_model.py
qianxing_openapi/response_struct.py
qianxing_openapi/sim_record.py
qianxing_openapi/sim_record_model.py
qianxing_openapi/simulator.py
qianxing_openapi/train_task.py
qianxing_openapi-0.1.8.dist-info/METADATA
qianxing_openapi-0.1.8.dist-info/WHEEL
qianxing_openapi-0.1.8.dist-info/top_level.txt
qianxing_openapi-0.1.8.dist-info/RECORD
