Metadata-Version: 2.1
Name: qianxing-openapi
Version: 0.1.8
Summary: Qianxing OpenAPI SDK for Python - A client library for accessing Qianxing's simulation platform
Home-page: https://github.com/risenlighten-qianxing/openapi-sdk-python
Author: Zhihong Luo
Author-email: luozhihong@risenlighten.com
Project-URL: Source, https://github.com/risenlighten-qianxing/openapi-sdk-python
Project-URL: Bug Reports, https://github.com/risenlighten-qianxing/openapi-sdk-python/issues
Keywords: Qianxing,Lasvsim,自动驾驶,OpenAPI,Simulation,Autonomous Driving
Classifier: Development Status :: 4 - Beta
Classifier: Intended Audience :: Developers
Classifier: License :: OSI Approved :: MIT License
Classifier: Programming Language :: Python :: 3
Classifier: Programming Language :: Python :: 3.7
Classifier: Programming Language :: Python :: 3.8
Classifier: Programming Language :: Python :: 3.9
Classifier: Programming Language :: Python :: 3.10
Classifier: Topic :: Software Development :: Libraries :: Python Modules
Requires-Python: >=3.0
Requires-Dist: requests >=2.25.0
